odoo/addons/web_widget_uom/README.rst
odoo/addons/web_widget_uom/__init__.py
odoo/addons/web_widget_uom/__manifest__.py
odoo/addons/web_widget_uom/i18n/it.po
odoo/addons/web_widget_uom/i18n/web_widget_uom.pot
odoo/addons/web_widget_uom/models/__init__.py
odoo/addons/web_widget_uom/models/uom_uom.py
odoo/addons/web_widget_uom/readme/CONTRIBUTORS.rst
odoo/addons/web_widget_uom/readme/DESCRIPTION.rst
odoo/addons/web_widget_uom/readme/ROADMAP.rst
odoo/addons/web_widget_uom/readme/USAGE.rst
odoo/addons/web_widget_uom/static/description/UoMDecimalPlaces.png
odoo/addons/web_widget_uom/static/description/icon.png
odoo/addons/web_widget_uom/static/description/index.html
odoo/addons/web_widget_uom/static/src/js/widget.js
odoo/addons/web_widget_uom/tests/__init__.py
odoo/addons/web_widget_uom/tests/test_decimal_precision.py
odoo/addons/web_widget_uom/views/assets.xml
odoo/addons/web_widget_uom/views/uom_uom_views.xml
odoo14_addon_web_widget_uom-14.0.1.0.1.dev3.dist-info/METADATA
odoo14_addon_web_widget_uom-14.0.1.0.1.dev3.dist-info/WHEEL
odoo14_addon_web_widget_uom-14.0.1.0.1.dev3.dist-info/top_level.txt
odoo14_addon_web_widget_uom-14.0.1.0.1.dev3.dist-info/RECORD
