Metadata-Version: 2.1
Name: odoo14-addon-web-widget-uom
Version: 14.0.1.0.1.dev3
Summary: Allow user to to decide how many decimal places should be displayed for UoM.
Home-page: https://github.com/OCA/web
Author: Odoo Community Association (OCA), Giovanni Serra
Author-email: support@odoo-community.org
License: AGPL-3
Platform: UNKNOWN
Classifier: Programming Language :: Python
Classifier: Framework :: Odoo
Classifier: Framework :: Odoo :: 14.0
Classifier: License :: OSI Approved :: GNU Affero General Public License v3
Requires-Python: >=3.6
Requires-Dist: odoo <14.1dev,>=14.0a
